cmdwatch/__init__.py
cmdwatch/__main__.py
cmdwatch-0.0.7.dist-info/LICENSE
cmdwatch-0.0.7.dist-info/METADATA
cmdwatch-0.0.7.dist-info/WHEEL
cmdwatch-0.0.7.dist-info/entry_points.txt
cmdwatch-0.0.7.dist-info/top_level.txt
cmdwatch-0.0.7.dist-info/RECORD
