Metadata-Version: 2.1
Name: cmdwatch
Version: 0.0.7
Summary: A CLI tool to watch for command outputs and store them to a file for further analysis
Home-page: https://github.com/eckarthik/cmdwatch
Author: Karthik E C
Author-email: eckarthik39@gmail.com
License: UNKNOWN
Platform: UNKNOWN
Classifier: Programming Language :: Python :: 3
Classifier: License :: OSI Approved :: MIT License
Classifier: Operating System :: OS Independent
Requires-Python: >=3.6
License-File: LICENSE
